youtubeinsights_mcp_server_test/__init__.py
youtubeinsights_mcp_server_test/server.py
youtubeinsights_mcp_server_test-0.1.0.dist-info/METADATA
youtubeinsights_mcp_server_test-0.1.0.dist-info/WHEEL
youtubeinsights_mcp_server_test-0.1.0.dist-info/entry_points.txt
youtubeinsights_mcp_server_test-0.1.0.dist-info/RECORD
