Metadata-Version: 2.4
Name: youtubeinsights-mcp-server-test
Version: 0.1.0
Summary: Add your description here
Author-email: hanalia <dabidstudio08@gmail.com>
Requires-Python: >=3.13
Requires-Dist: build>=1.2.2.post1
Requires-Dist: mcp>=1.7.1
Requires-Dist: python-dotenv>=1.1.0
Requires-Dist: requests>=2.32.3
Requires-Dist: twine>=6.1.0
Requires-Dist: youtube-transcript-api>=1.0.3
